README.md
setup.py
icndb_sdk/__init__.py
icndb_sdk/main.py
icndb_sdk.egg-info/PKG-INFO
icndb_sdk.egg-info/SOURCES.txt
icndb_sdk.egg-info/dependency_links.txt
icndb_sdk.egg-info/requires.txt
icndb_sdk.egg-info/top_level.txt